[
  {
    "universal_id": "114c7421-9f74-459c-a93f-acbd82810b97",
    "svg_filename": "notehead_114c7421_P1_A4_M4.svg",
    "coordinates": {
      "svg_x": 3178,
      "svg_y": 1049,
      "staff_index": 0
    },
    "visual_data": {
      "notehead_code": 102,
      "unicode_char": "&#102;",
      "duration": "quarter"
    },
    "instrument_info": {
      "part_id": "P1",
      "measure": 4
    }
  },
  {
    "universal_id": "ee310a4b-2a90-40f3-a93f-828578be3b99",
    "svg_filename": "notehead_ee310a4b_P1_A4_M5.svg",
    "coordinates": {
      "svg_x": 3454,
      "svg_y": 1049,
      "staff_index": 0
    },
    "visual_data": {
      "notehead_code": 102,
      "unicode_char": "&#102;",
      "duration": "eighth"
    },
    "instrument_info": {
      "part_id": "P1",
      "measure": 5
    }
  },
  {
    "universal_id": "e70c3338-a28b-41f2-a3ed-d03b0c02a43f",
    "svg_filename": "notehead_e70c3338_P1_G4_M5.svg",
    "coordinates": {
      "svg_x": 3617,
      "svg_y": 1043,
      "staff_index": 0
    },
    "visual_data": {
      "notehead_code": 102,
      "unicode_char": "&#102;",
      "duration": "quarter"
    },
    "instrument_info": {
      "part_id": "P1",
      "measure": 5
    }
  },
  {
    "universal_id": "9cc4726b-046b-430d-b858-c3923ea0aa73",
    "svg_filename": "notehead_9cc4726b_P2_B3_M4.svg",
    "coordinates": {
      "svg_x": 2722,
      "svg_y": 1393,
      "staff_index": 1
    },
    "visual_data": {
      "notehead_code": 70,
      "unicode_char": "&#70;",
      "duration": "half"
    },
    "instrument_info": {
      "part_id": "P2",
      "measure": 4
    }
  },
  {
    "universal_id": "5879aa52-e2c9-48c2-8232-a85e7a7ff5d9",
    "svg_filename": "notehead_5879aa52_P2_B3_M4.svg",
    "coordinates": {
      "svg_x": 3178,
      "svg_y": 1393,
      "staff_index": 1
    },
    "visual_data": {
      "notehead_code": 102,
      "unicode_char": "&#102;",
      "duration": "quarter"
    },
    "instrument_info": {
      "part_id": "P2",
      "measure": 4
    }
  },
  {
    "universal_id": "101d0cd6-0e90-42fe-adab-9278cefebb6b",
    "svg_filename": "notehead_101d0cd6_P2_B3_M5.svg",
    "coordinates": {
      "svg_x": 3454,
      "svg_y": 1393,
      "staff_index": 1
    },
    "visual_data": {
      "notehead_code": 102,
      "unicode_char": "&#102;",
      "duration": "eighth"
    },
    "instrument_info": {
      "part_id": "P2",
      "measure": 5
    }
  },
  {
    "universal_id": "6a6116f1-1adc-48ac-82ee-36f9356afdc5",
    "svg_filename": "notehead_6a6116f1_P2_A3_M5.svg",
    "coordinates": {
      "svg_x": 3617,
      "svg_y": 1393,
      "staff_index": 1
    },
    "visual_data": {
      "notehead_code": 102,
      "unicode_char": "&#102;",
      "duration": "quarter"
    },
    "instrument_info": {
      "part_id": "P2",
      "measure": 5
    }
  },
  {
    "universal_id": "18cd6281-edac-412c-9d8e-149d7aa889c3",
    "svg_filename": "notehead_18cd6281_P2_C4_M5.svg",
    "coordinates": {
      "svg_x": 3841,
      "svg_y": 1399,
      "staff_index": 1
    },
    "visual_data": {
      "notehead_code": 102,
      "unicode_char": "&#102;",
      "duration": "eighth"
    },
    "instrument_info": {
      "part_id": "P2",
      "measure": 5
    }
  },
  {
    "universal_id": "9f9ce0a1-7533-4521-970c-a2facd18c515",
    "svg_filename": "notehead_9f9ce0a1_P2_B3_M5.svg",
    "coordinates": {
      "svg_x": 4005,
      "svg_y": 1393,
      "staff_index": 1
    },
    "visual_data": {
      "notehead_code": 102,
      "unicode_char": "&#102;",
      "duration": "quarter"
    },
    "instrument_info": {
      "part_id": "P2",
      "measure": 5
    }
  }
]